core_processes/__init__.py
core_processes/cobra_process.py
core_processes/copasi_process.py
core_processes/smoldyn_process.py
core_processes/tellurium_process.py
core_processes/tests/__init__.py
core_processes/tests/test_cobra.py
core_processes/tests/test_copasi.py
core_processes/tests/test_smoldyn.py
core_processes/tests/test_tellurium.py
core_processes-0.0.2.dist-info/AUTHORS.md
core_processes-0.0.2.dist-info/LICENSE
core_processes-0.0.2.dist-info/METADATA
core_processes-0.0.2.dist-info/WHEEL
core_processes-0.0.2.dist-info/top_level.txt
core_processes-0.0.2.dist-info/RECORD
