Metadata-Version: 2.1
Name: core-processes
Version: 0.0.2
Home-page: https://github.com/vivarium-collective/process-bigraph
Author: Ryan Spangler, Eran Agmon, Alex Patrie
Author-email: ryan.spangler@gmail.com, agmon.eran@gmail.com, alexanderpatrie@gmail.com
Classifier: Development Status :: 3 - Alpha
Classifier: Intended Audience :: Developers
Classifier: License :: OSI Approved :: MIT License
Classifier: Operating System :: OS Independent
Classifier: Programming Language :: Python
Classifier: Programming Language :: Python :: 3
Classifier: Programming Language :: Python :: 3.6
Classifier: Programming Language :: Python :: 3.7
Classifier: Programming Language :: Python :: 3.8
Classifier: Programming Language :: Python :: 3.9
Classifier: Programming Language :: Python :: 3.10
Classifier: Programming Language :: Python :: 3.11
Requires-Python: >=3.6
License-File: LICENSE
License-File: AUTHORS.md
Requires-Dist: bigraph-schema
Requires-Dist: process-bigraph
Requires-Dist: numpy
Requires-Dist: pytest >=6.2.5
Provides-Extra: cobra
Requires-Dist: cobra ; extra == 'cobra'
Provides-Extra: copasi
Requires-Dist: copasi-basico ; extra == 'copasi'
Provides-Extra: smoldyn
Requires-Dist: smoldyn ; extra == 'smoldyn'
Requires-Dist: simulariumio ; extra == 'smoldyn'
Provides-Extra: tellurium
Requires-Dist: tellurium ; extra == 'tellurium'
